discovery/__init__.py
discovery/registry.py
django_discovery-0.0.6.dist-info/DESCRIPTION.rst
django_discovery-0.0.6.dist-info/METADATA
django_discovery-0.0.6.dist-info/RECORD
django_discovery-0.0.6.dist-info/WHEEL
django_discovery-0.0.6.dist-info/metadata.json
django_discovery-0.0.6.dist-info/top_level.txt
tests/__init__.py
tests/test_dns_registry.py
tests/test_docker_registry.py
tests/test_environment_registry.py
tests/test_initialization.py
