Metadata-Version: 2.0
Name: django-discovery
Version: 0.0.6
Summary: Docker service discovery for Django
Home-page: https://github.com/formikejo/django-discovery
Author: Yigal Duppen
Author-email: yigal@publysher.nl
License: MIT
Keywords: django service-discovery docker docker-compose
Platform: UNKNOWN
Classifier: Development Status :: 3 - Alpha
Classifier: Intended Audience :: Developers
Classifier: Topic :: Software Development :: Libraries
Classifier: Framework :: Django :: 1.8
Classifier: License :: OSI Approved :: MIT License
Classifier: Programming Language :: Python :: 3
Classifier: Programming Language :: Python :: 3.4
Requires-Dist: Django (>=1.8)
Requires-Dist: dnspython3 (>=1.12.0)
Requires-Dist: docker-py (>=1.4.0)
